async_pytest_httpserver/__init__.py
async_pytest_httpserver/fixtures.py
async_pytest_httpserver/py.typed
async_pytest_httpserver/web_service_mock.py
async_pytest_httpserver-1.0.1.dist-info/METADATA
async_pytest_httpserver-1.0.1.dist-info/WHEEL
async_pytest_httpserver-1.0.1.dist-info/licenses/LICENSE
async_pytest_httpserver-1.0.1.dist-info/RECORD
