Metadata-Version: 2.4
Name: async-pytest-httpserver
Version: 1.0.1
Summary: Async mock HTTP server for pytest, built on top of aiohttp.
Project-URL: Homepage, https://github.com/krylosov-aa/async-pytest-httpserver
Author-email: krylosov-aa <krylosov.andrew@gmail.com>
License: MIT
License-File: LICENSE
Requires-Python: >=3.13
Requires-Dist: aiohttp>=3.13.2
Requires-Dist: pytest-aiohttp>=1.1.0
Requires-Dist: pytest-asyncio>=1.3.0
Requires-Dist: pytest>=9.0.2
